{"T3wPjuwleDI23LDWp42Wuw==":"img105.jpg","UeXxpg7vLj1oUHwP0NxhSw==":"img93.jpg","MHOERdILU+faLSiORzVStw==":"img127.jpg","24X4uLRxM5UDgdF3Ajl3SA==":"img81.jpg","xgxoWtetJRHjBapbNHDx9A==":"2021-09-11-22-17-33-removebg-preview.png","703jGkvtoXpxbZTG7S89UA==":"features2.jpg","Cesjxe6cW0NYFSAP4kiRig==":"features1.jpg","HUfpc9SvDwBk7sbVG2SgiA==":"features3.jpg","oRykAiO0rUD++7AmPeEwUg==":"background1.jpg","WeIcOp+qLfFEPxVAXUUAEA==":"features4.jpg","UKHbrmTqYT7ohxZQR+10oA==":"img77.jpg","UIqqlEnNVKs7yTLb/6yqcA==":"img61.jpg","bAfWWWqKNZoJ+0r7MWXTbg==":"10.jpg","yapJmg/ervViAuWx/KkN6A==":"11.jpg","+hCivPZOpYOC9nSpwosVTQ==":"13.jpg","PCWbGQ17U2APhhLB7wMTEg==":"14.jpg","1PXv7/43PW0HyZJnX+TJvQ==":"16.jpg","Pq9GM+6+cp7jDexBxltvyg==":"2.jpg","sFbL00EhvkWma64M0JjU4A==":"7.jpg","ZOnXH/mI5VmCDTGI6OWETA==":"8.jpg","wQyvD6UuDTVrkiTDz9Ibkg==":"4.jpg","tA9T542VmwfbmVZ87w1bFA==":"3.jpg","wgqf0GJEbFr4RPTyN7ciig==":"17.jpg","Zn1pWmLt9u2v5b7gMn3Hwg==":"18.jpg","IR50eEAa/gjv9e3Jv2cWTg==":"background5.jpg","7uIPENP6xrQaAH0UKqefvQ==":"mbr-116x116.jpg","dL5bkngufUjtOttIqd/jGw==":"mbr-1920x1282.jpg","bOt2vglr9rHR6nTVg2PaHA==":"mbr-1920x1280.jpg","NcWMAwZSd0irFaFslX8T3w==":"mbr-1920x1273.jpg","fcpbkyfcSenUwDdMn6zlUw==":"mbr-1920x1080.jpg","eLGunz+TXc/OP+nEBU1OAQ==":"mbr-495x330.jpg","zi4z3zmwbiwCQddovwf4Qw==":"mbr-1-495x330.jpg","SoscUyNMmIkf9aw4I0JqDQ==":"mbr-2-495x330.jpg","7APH7LctS6sE/VxnXCG5tw==":"mbr-3-495x330.jpg","1QWhbALvUaBErH+7fckySA==":"mbr-495x278.jpg","lPbM/jp0TBImcGMN+uQEZQ==":"mbr-4-495x330.jpg","8RuuFtwc3CbhVWh8HFonqg==":"mbr-5-495x330.jpg","41cWYfbNbeCH/rdkoQfyLg==":"mbr-1-1920x1282.jpg","MYbav5bjgqqlGE6DJ3zhAw==":"background1-1.jpg","4Gntodxl3ALRuHYDhcoZkQ==":"mbr-970x693.jpg","uHMr40QJPTsTbqozNRX+Ww==":"mbr-865x577.jpg","JcKCw+YXZd5ga7VnOrOrIw==":"mbr-1-1920x1280.jpg","53TMhAclIAFz5k+gvglCxQ==":"mbr-97x76.png","3QOGI8BEvyti8cOv0IaHNw==":"mbr-1920x898.jpg","g4mbVTG45SIbop3r00IQag==":"mbr-2-1920x1280.jpg","MhpUgjhWS+N9MqLmrVJ80Q==":"ezgif.com-gif-maker%20(1).gif","wFCZkIC/4SmJJtYl0PRcCg==":"onlinelogomaker-111321-2354-4106-2000-transparent-122x26.png","pV/98QXAutVp9gheUpUpEQ==":"onlinelogomaker-111321-2354-4106-2000-transparent-450x94.png","t2sVWuvjypkrzD5DNw1IMA==":"%E2%80%94pngtree%E2%80%94hand%20drawn%20school%20supplies%20graduation-1219921-1920x1371.jpg","rXm7RLGqAEAoAsNuKEWc9g==":"slide3-1024x768.jpg","344uqhmHjV3HSRTFojPftA==":"%E2%80%94pngtree%E2%80%94hand%20drawn%20school%20supplies%20graduation-1219921-2000x1428.jpg","87PJcAfFxb3L8Ebi143bQQ==":"%E2%80%94pngtree%E2%80%94hand%20drawn%20school%20supplies%20graduation-1219921-1024x768.jpg","Ipd1n4VdvlvGNEwwvHYYSw==":"%E2%80%94pngtree%E2%80%94hand%20drawn%20school%20supplies%20graduation-1219921-85x48.png","zk8dIEy6qeV2jhwtkXCEzA==":"slide2.jpg","JeT0iBExrlNhcVgxA6Xe1A==":"slide2-1024x576.jpg","Z/Buc0E4osejIrUiLkLQ9A==":"mbr-5-1024x576.jpg","rIDnWBcxErjThy+p33nrwg==":"mbr-1-1024x576.jpg","nq//otRYomrfLWU70WCYkw==":"mbr-1-1600x1080.jpg","1pY1Ikq29QbGtMkBhKpDXg==":"%E2%80%94pngtree%E2%80%94hand%20drawn%20school%20supplies%20graduation-1219921-1600x1080.jpg","PtUJ+NdKSPo8WYn/JIHNug==":"mbr-7-1600x1080.jpg"}